scrivenor/tools.py
scrivenor-1.0.1.dist-info/top_level.txt
scrivenor-1.0.1.dist-info/METADATA
scrivenor-1.0.1.dist-info/DESCRIPTION.rst
scrivenor-1.0.1.dist-info/metadata.json
scrivenor-1.0.1.dist-info/WHEEL
scrivenor-1.0.1.dist-info/RECORD
